jpegdupes/__init__.py
jpegdupes/jpegdupes.py
jpegdupes-2.1.0.dist-info/LICENSE
jpegdupes-2.1.0.dist-info/METADATA
jpegdupes-2.1.0.dist-info/WHEEL
jpegdupes-2.1.0.dist-info/entry_points.txt
jpegdupes-2.1.0.dist-info/top_level.txt
jpegdupes-2.1.0.dist-info/RECORD
