Metadata-Version: 2.1
Name: jpegdupes
Version: 2.1.0
Summary: Image duplicate finder that ignores JPEG metadata
Home-page: https://github.com/jesjimher/imgdupes
Author: Jesús Jiménez
Author-email: jesjimenez@gmail.com
License: UNKNOWN
Keywords: image duplicate finder metadata jpeg
Platform: UNKNOWN
Classifier: Programming Language :: Python :: 3
Classifier: License :: OSI Approved :: GNU General Public License v3 (GPLv3)
Classifier: Operating System :: OS Independent
Requires-Python: >=3
Requires-Dist: texttable
Requires-Dist: jpegtran-cffi (>0.5)
Requires-Dist: Pillow
